realiseven/__init__.py
realiseven/core.py
realiseven/models.py
realiseven-0.1.0.dist-info/LICENSE
realiseven-0.1.0.dist-info/METADATA
realiseven-0.1.0.dist-info/WHEEL
realiseven-0.1.0.dist-info/top_level.txt
realiseven-0.1.0.dist-info/RECORD
