Metadata-Version: 2.1
Name: realiseven
Version: 0.1.0
Summary: AI-Powered library to determine if number is even or odd.
Home-page: https://github.com/kreiza/realiseven
Author: Dmytro Kreiza
Author-email: d.kreiza.dev.news@gmail.com
Classifier: Programming Language :: Python :: 3
Classifier: License :: OSI Approved :: MIT License
Classifier: Operating System :: OS Independent
Requires-Python: >=3.8
License-File: LICENSE
Requires-Dist: openai~=1.65.4
Requires-Dist: pydantic~=2.10.6
